kan_alexandria/__init__.py
kan_alexandria/__main__.py
kan_alexandria/__version__.py
kan_alexandria/book_api.py
kan_alexandria/models.py
kan_alexandria/structures.py
kan_alexandria-0.0.6.dist-info/LICENSE.md
kan_alexandria-0.0.6.dist-info/METADATA
kan_alexandria-0.0.6.dist-info/WHEEL
kan_alexandria-0.0.6.dist-info/entry_points.txt
kan_alexandria-0.0.6.dist-info/top_level.txt
kan_alexandria-0.0.6.dist-info/RECORD
