Metadata-Version: 2.1
Name: kan-alexandria
Version: 0.0.6
Summary: Kan_Alexandria is Python 3.5+ library for searching book details using Google Books API. It's based on the original Kan module but optimized for consumption of more data and returns the data in a more usable format (Python dicts). 
Home-page: https://github.com/joaodath/kan_alexandria
Author: Sang Han, João Rodrigues
Author-email: joaorodriguesdiasneto@gmail.com
License: Apache License
Download-URL: https://github.com/joaodath/kan_alexandria.git
Project-URL: Bug Tracker, https://github.com/joaodath/kan_alexandria/issues
Platform: UNKNOWN
Classifier: Development Status :: 5 - Production/Stable
Classifier: Environment :: Console
Classifier: Intended Audience :: Developers
Classifier: Natural Language :: English
Classifier: License :: OSI Approved :: Apache Software License
Classifier: Operating System :: OS Independent
Classifier: Programming Language :: Unix Shell
Classifier: Programming Language :: Python
Classifier: Programming Language :: Python :: 2.7
Classifier: Programming Language :: Python :: 3.3
Classifier: Programming Language :: Python :: 3.4
Classifier: Topic :: Software Development :: Libraries :: Python Modules
Classifier: Topic :: Text Processing :: Linguistic
Classifier: Topic :: Utilities
Requires-Python: >=3.6
License-File: LICENSE.md
